pycoin_rs/__init__.py
pycoin_rs/pycoin_rs.pypy37-pp73-darwin.so
pycoin_rs-0.1.0.dist-info/RECORD
pycoin_rs-0.1.0.dist-info/WHEEL
pycoin_rs-0.1.0.dist-info/METADATA
