Metadata-Version: 2.1
Name: pycoin_rs
Version: 0.1.0
Classifier: Programming Language :: Rust
Classifier: Programming Language :: Python :: Implementation :: CPython
Classifier: Programming Language :: Python :: Implementation :: PyPy
License: MIT
Requires-Python: >=3.7
